Metadata-Version: 2.1
Name: csv-diff
Version: 1.2
Summary: Python CLI tool and library for diffing CSV and JSON files
Home-page: https://github.com/simonw/csv-diff
Author: Simon Willison
License: Apache License, Version 2.0
Classifier: Development Status :: 4 - Beta
Classifier: Intended Audience :: Developers
Classifier: Intended Audience :: Science/Research
Classifier: Intended Audience :: End Users/Desktop
Classifier: License :: OSI Approved :: Apache Software License
Classifier: Programming Language :: Python :: 3.6
Classifier: Programming Language :: Python :: 3.7
License-File: LICENSE
Requires-Dist: click
Requires-Dist: dictdiffer
Provides-Extra: test
Requires-Dist: pytest; extra == "test"
